combinatorial_gwas/__init__.py
combinatorial_gwas/_high_level_old.py
combinatorial_gwas/_nbdev.py
combinatorial_gwas/data_catalog.py
combinatorial_gwas/genotype.py
combinatorial_gwas/high_level.py
combinatorial_gwas/phenotypes/Field.py
combinatorial_gwas/phenotypes/__init__.py
combinatorial_gwas/simulation.py
combinatorial_gwas/training/__init__.py
combinatorial_gwas/training/cnn.py
combinatorial_gwas-0.2.1.dist-info/LICENSE
combinatorial_gwas-0.2.1.dist-info/WHEEL
combinatorial_gwas-0.2.1.dist-info/METADATA
combinatorial_gwas-0.2.1.dist-info/RECORD
