Metadata-Version: 2.1
Name: combinatorial-gwas
Version: 0.2.1
Summary: A package for the final project of MIT's 6.874 class Deep Learning in Life Science
Author: anhoang
Author-email: anhoang@wi.mit.edu
Requires-Python: >=3.8,<3.9
Classifier: Programming Language :: Python :: 3
Classifier: Programming Language :: Python :: 3.8
Requires-Dist: aiohttp (>=3.7.4,<4.0.0)
Requires-Dist: apricot-select (>=0.6.1,<0.7.0)
Requires-Dist: bgen-reader (>=4.0.7,<5.0.0)
Requires-Dist: bokeh (>=2.3.1,<3.0.0)
Requires-Dist: colorcet (>=2.0.6,<3.0.0)
Requires-Dist: datashader (>=0.12.1,<0.13.0)
Requires-Dist: deeplift (>=0.6.13,<0.7.0)
Requires-Dist: fastparquet (>=0.5.0,<0.6.0)
Requires-Dist: holoviews (>=1.14.3,<2.0.0)
Requires-Dist: keras-tuner (>=1.0.2,<2.0.0)
Requires-Dist: matplotlib (>=3.4.1,<4.0.0)
Requires-Dist: pandas (>=1.2.4,<2.0.0)
Requires-Dist: pca (>=1.4.0,<2.0.0)
Requires-Dist: pydantic (>=1.8.1,<2.0.0)
Requires-Dist: requests (>=2.25.1,<3.0.0)
Requires-Dist: scikit-image (>=0.18.1,<0.19.0)
Requires-Dist: seaborn (>=0.11.1,<0.12.0)
Requires-Dist: shap (>=0.39.0,<0.40.0)
Requires-Dist: statsmodels (>=0.12.2,<0.13.0)
Requires-Dist: umap-learn (>=0.5.1,<0.6.0)
